plugin_jm_server/__init__.py
plugin_jm_server/app.py
plugin_jm_server/driver.py
plugin_jm_server/files.py
plugin_jm_server/static/css/all.min.css
plugin_jm_server/static/css/bootstrap.css
plugin_jm_server/static/css/download_error.css
plugin_jm_server/static/css/index.css
plugin_jm_server/static/css/index_spa.css
plugin_jm_server/static/css/login.css
plugin_jm_server/static/css/style_photo.css
plugin_jm_server/static/css/upload.css
plugin_jm_server/static/css/h5/m_download_error.css
plugin_jm_server/static/css/h5/m_index.css
plugin_jm_server/static/css/h5/m_login.css
plugin_jm_server/static/css/h5/m_upload.css
plugin_jm_server/static/css/h5/normalize.css
plugin_jm_server/static/img/bg.jpg
plugin_jm_server/static/img/m_bg.jpeg
plugin_jm_server/static/js/common.js
plugin_jm_server/static/js/index.js
plugin_jm_server/static/js/index_spa.js
plugin_jm_server/static/js/jquery-3.7.1.min.js
plugin_jm_server/static/js/jquery.album-0.2.js
plugin_jm_server/static/js/jquery.lazyload-2.0.js
plugin_jm_server/static/js/jquery.photo-0.3.js
plugin_jm_server/static/js/upload.js
plugin_jm_server/static/js/h5/m_index.js
plugin_jm_server/static/js/h5/m_upload.js
plugin_jm_server/static/webfonts/fa-regular-400.woff2
plugin_jm_server/static/webfonts/fa-solid-900.woff2
plugin_jm_server/templates/download_error.html
plugin_jm_server/templates/index.html
plugin_jm_server/templates/index_spa.html
plugin_jm_server/templates/jm_view.html
plugin_jm_server/templates/login.html
plugin_jm_server/templates/m_download_error.html
plugin_jm_server/templates/m_index.html
plugin_jm_server/templates/m_jm_view.html
plugin_jm_server/templates/m_login.html
plugin_jm_server/templates/m_upload.html
plugin_jm_server/templates/upload.html
plugin_jm_server-0.2.0.dist-info/METADATA
plugin_jm_server-0.2.0.dist-info/WHEEL
plugin_jm_server-0.2.0.dist-info/top_level.txt
plugin_jm_server-0.2.0.dist-info/RECORD
