Metadata-Version: 2.4
Name: plugin_jm_server
Version: 0.2.0
Summary: plugin_jm_server, a plugin for jmcomic that can be used to view comics in a web browser.
Home-page: https://github.com/hect0x7/plugin-jm-server
Author: hect0x7
Author-email: 93357912+hect0x7@users.noreply.github.com
Keywords: python,jmcomic,18comic,禁漫天堂,NSFW
Classifier: Development Status :: 4 - Beta
Classifier: Intended Audience :: Developers
Classifier: Programming Language :: Python :: 3.7
Classifier: Programming Language :: Python :: 3.8
Classifier: Programming Language :: Python :: 3.9
Classifier: Programming Language :: Python :: 3.10
Classifier: Programming Language :: Python :: 3.11
Classifier: Programming Language :: Python :: 3.12
Classifier: Operating System :: MacOS
Classifier: Operating System :: POSIX :: Linux
Classifier: Operating System :: Microsoft :: Windows
Requires-Python: >=3.7
Requires-Dist: jmcomic
Requires-Dist: flask
Requires-Dist: psutil
Requires-Dist: cryptography
Dynamic: author
Dynamic: author-email
Dynamic: classifier
Dynamic: description
Dynamic: description-content-type
Dynamic: home-page
Dynamic: keywords
Dynamic: requires-dist
Dynamic: requires-python
Dynamic: summary
